opsworkssmoothdeploy
