Metadata-Version: 1.1
Name: aws-opsworks-smooth-deploy
Version: 0.1.8
Summary: Smooth Deploy on AWS Opsworks 
Home-page: https://github.com/urbanindo/aws-opsworks-smooth-deploy
Author: Rifki, Petra Barus
Author-email: rifki@urbanindo.com, petra@urbanindo.com
License: UNKNOWN
Keywords: aws,opsworks
Platform: UNKNOWN
Classifier: Development Status :: 3 - Alpha
Classifier: Topic :: Utilities
